hyve_pyipmi-1.2.5.data/scripts/pyipmi
hyve_pyipmi-1.2.5.data/scripts/pyipmr
hyve_pyipmi-1.2.5.data/scripts/pyping
hyve_pyipmi-1.2.5.data/scripts/pysh
pyipmi/__init__.py
pyipmi/cmds/__init__.py
pyipmi/cmds/_chassis.py
pyipmi/cmds/_common.py
pyipmi/cmds/_consts.py
pyipmi/cmds/_event.py
pyipmi/cmds/_fru.py
pyipmi/cmds/_lan.py
pyipmi/cmds/_mc.py
pyipmi/cmds/_power.py
pyipmi/cmds/_raw.py
pyipmi/cmds/_sdr.py
pyipmi/cmds/_sel.py
pyipmi/cmds/_sensor.py
pyipmi/cmds/_user.py
pyipmi/cmds/pyshell.py
pyipmi/intf/__init__.py
pyipmi/intf/_crypto.py
pyipmi/intf/_rakp.py
pyipmi/intf/_rmcp_msg.py
pyipmi/intf/_rmcpp_msg.py
pyipmi/intf/kcs.py
pyipmi/intf/rmcp.py
pyipmi/intf/rmcpp.py
pyipmi/intf/ioctl/__init__.py
pyipmi/mesg/__init__.py
pyipmi/mesg/ipmi_app.py
pyipmi/mesg/ipmi_chassis.py
pyipmi/mesg/ipmi_se.py
pyipmi/mesg/ipmi_storage.py
pyipmi/mesg/ipmi_transport.py
pyipmi/util/__init__.py
pyipmi/util/config.py
pyipmi/util/exception.py
hyve_pyipmi-1.2.5.dist-info/LICENSE
hyve_pyipmi-1.2.5.dist-info/METADATA
hyve_pyipmi-1.2.5.dist-info/WHEEL
hyve_pyipmi-1.2.5.dist-info/top_level.txt
hyve_pyipmi-1.2.5.dist-info/RECORD
