Metadata-Version: 2.1
Name: hyve-pyipmi
Version: 1.2.5
Summary: Pure Python-based IPMI client developed by Hyve Design Solutions.
Home-page: https://github.com/hyvedesignsolutions/hyve-pyipmi
Author: Janny Au
Author-email: jannya@hyvedesignsolutions.com
License: BSD 3-Clause License
Keywords: ipmi,rmcp,rmcpp,kcs,openipmi
Platform: linux
Platform: windows
Classifier: Programming Language :: Python :: 3
Classifier: License :: OSI Approved :: BSD License
Classifier: Operating System :: OS Independent
Requires-Python: >=3.6
Requires-Dist: cryptography
Requires-Dist: pycrypto
